{
  "capital": 1000.0,
  "capital_max": 1000.0,
  "posiciones": [
    {
      "simbolo": "ETH_USDT",
      "dir": "short",
      "calidad": "nivel1",
      "precio_entrada": 2316.2413,
      "precio_ref": 2316.2413,
      "sl": 2332.6796,
      "tp": 2289.89672,
      "liq": 2838.8150000000005,
      "margen": 96.0,
      "lev": 4,
      "hora_entrada": 493654,
      "max_horas": 48,
      "trailing": false,
      "ts_entrada": "2026-04-25 21:00:00",
      "adaptive_factor": 1.0,
      "modo_sltp": "NIVEL",
      "sl_nivel": "MAX20",
      "tp_nivel": "ATR_fallback",
      "atr_entrada": 7.436534
    },
    {
      "simbolo": "BNB_USDT",
      "dir": "short",
      "calidad": "nivel2",
      "precio_entrada": 629.3851500000001,
      "precio_ref": 629.3851500000001,
      "sl": 634.93806,
      "tp": 618.176268,
      "liq": 676.9275,
      "margen": 168.0,
      "lev": 12,
      "hora_entrada": 493654,
      "max_horas": 48,
      "trailing": false,
      "ts_entrada": "2026-04-25 21:00:00",
      "adaptive_factor": 1.0,
      "modo_sltp": "NIVEL",
      "sl_nivel": "FIB_618",
      "tp_nivel": "ATR_fallback",
      "atr_entrada": 1.725422
    }
  ],
  "bot_activo": true,
  "en_pausa": false,
  "fin_pausa_hora": null,
  "n_ops": 0,
  "n_wins": 0,
  "n_loses": 0,
  "pnl_total": 0.0,
  "funding_total": 0.0,
  "ops_hoy": [],
  "ultima_ejecucion": "2026-04-25T22:07:44.186947+00:00",
  "primera_ejecucion": false
}