{
  "capital": 1000.0,
  "capital_max": 1000.0,
  "posiciones": [
    {
      "simbolo": "BTC_USDT",
      "dir": "short",
      "calidad": "elite",
      "precio_entrada": 78888.3361,
      "precio_ref": 78640.3,
      "sl": 79688.0195,
      "tp": 77288.96930000001,
      "liq": 83621.636266,
      "margen": 325.0,
      "lev": 15,
      "hora_entrada": 493578,
      "trailing": false,
      "ts_entrada": "2026-04-22 17:00:00",
      "adaptive_factor": 1.0,
      "modo_sltp": "REBOTE"
    },
    {
      "simbolo": "ETH_USDT",
      "dir": "short",
      "calidad": "elite",
      "precio_entrada": 2398.22029,
      "precio_ref": 2398.22029,
      "sl": 2430.04855,
      "tp": 2334.56377,
      "liq": 2542.1135074000003,
      "margen": 325.0,
      "lev": 15,
      "hora_entrada": 493578,
      "trailing": false,
      "ts_entrada": "2026-04-22 17:00:00",
      "adaptive_factor": 1.0,
      "modo_sltp": "REBOTE"
    },
    {
      "simbolo": "BNB_USDT",
      "dir": "short",
      "calidad": "elite",
      "precio_entrada": 644.59754,
      "precio_ref": 639.75,
      "sl": 650.3995761616071,
      "tp": 630.0924495959822,
      "liq": 683.2733924,
      "margen": 299.0,
      "lev": 15,
      "hora_entrada": 493578,
      "trailing": false,
      "ts_entrada": "2026-04-22 17:00:00",
      "adaptive_factor": 1.0,
      "modo_sltp": "ESTANDAR"
    }
  ],
  "bot_activo": true,
  "en_pausa": false,
  "fin_pausa_hora": null,
  "n_ops": 0,
  "n_wins": 0,
  "n_loses": 0,
  "pnl_total": 0.0,
  "funding_total": 0.0,
  "ops_hoy": [],
  "ultima_ejecucion": "2026-04-22T23:01:40.338720+00:00",
  "primera_ejecucion": false
}